[ 
    {
        "title": "Light Scroll Effect",
        "tech": "HTML, CSS, JavaScript",
        "image": "./assets/day1.png",
        "button-git": "Github",
        "button-demo":"Demo",
        "githubLink": "https://github.com/majazimnoch/js-day1",
        "demoLink": "https://thriving-kangaroo-eddb6d.netlify.app/",
        "comment": "My first project! I practised adding event listeners and learnt about mouse coordinates."
    },
    {
        "title": "Expanding Gallery",
        "tech": "HTML, CSS",
        "image": "./assets/day2.png",
        "button-git": "Github",
        "button-demo":"Demo",
        "githubLink": "https://github.com/majazimnoch/code-day2",
        "demoLink": "https://adorable-gumption-6b5044.netlify.app/",
        "comment": "Here I worked with styling using e.g. pseudo-classes in CSS."
    },
    {
        "title": "Stopwatch",
        "tech": "HTML, CSS, JavaScript",
        "image": "./assets/day3.png",
        "button-git": "Github",
        "button-demo":"Demo",
        "githubLink": "https://github.com/majazimnoch/code-day3",
        "demoLink": "https://bejewelled-lebkuchen-362c65.netlify.app/",
        "comment": "This time I use querySelector to selects the DOM objects. UpdateTime function calculates the elapsed time, while pad function formats the time."
    },
    {
        "title": "Sound and Image Effect on Click",
        "tech": "HTML, CSS, JavaScript",
        "image": "./assets/day4.png",
        "button-git": "Github",
        "button-demo":"Demo",
        "githubLink": "https://github.com/majazimnoch/code-day4-5",
        "demoLink": "https://playful-semifreddo-9ec36e.netlify.app/",
        "comment": "I work with Audio object and conditional rendering."
    },

    {
        "title": "Color Picker",
        "tech": "HTML, CSS, JavaScript",
        "image": "./assets/day6.png",
        "button-git": "Github",
        "button-demo":"Demo",
        "githubLink": "https://github.com/majazimnoch/code-day6",
        "demoLink": "https://relaxed-narwhal-ebd84f.netlify.app/",
        "comment": "Here I practise random() and floor() methods of Math object. I also convert number to string."
    }, 

    {
        "title": "Visual Effect using Particles library",
        "tech": "HTML, CSS, JavaScript, Particles",
        "image": "./assets/day7.png",
        "button-git": "Github",
        "button-demo":"Demo",
        "githubLink": "https://github.com/majazimnoch/code-day7",
        "demoLink": "https://coruscating-duckanoo-6f9f91.netlify.app/",
        "comment": "Time to use a popular library Particles!"
    },

    {
        "title": "Confetti Effect",
        "tech": "HTML, CSS, JavaScript, Particles",
        "image": "./assets/day8.png",
        "button-git": "Github",
        "button-demo":"Demo",
        "githubLink": "https://github.com/majazimnoch/code-day8",
        "demoLink": "https://jocular-seahorse-015f0c.netlify.app/",
        "comment": "Here another library, attached to HTML file through a script tag (CDN)."
    },

    {
        "title": "News Generator",
        "tech": "HTML, CSS, JavaScript, REST API",
        "image": "./assets/day9.png",
        "button-git": "Github",
        "button-demo":"Demo",
        "githubLink": "https://github.com/majazimnoch/code-day9",
        "demoLink": "https://silver-piroshki-7c92ba.netlify.app/",
        "comment": "Here I fetch from an API to display some information from newspapers base."
    }, 

    {
        "title": "Button that Runs Away",
        "tech": "HTML, CSS, JavaScript",
        "image": "./assets/day10.png",
        "button-git": "Github",
        "button-demo":"Demo",
        "githubLink": "https://github.com/majazimnoch/code-day10",
        "demoLink": "https://date-me-love.netlify.app/",
        "comment": "It's quite a lot of code to make this logic works!"
    },

    {
        "title": "Who is in space now?",
        "tech": "HTML, CSS, JavaScript, API, LottieFiles",
        "image": "./assets/day11.png",
        "button-git": "Github",
        "button-demo":"Demo",
        "githubLink": "https://github.com/majazimnoch/code-day11",
        "demoLink": "https://fantastic-hamster-a2725c.netlify.app/",
        "comment": "Here I fetch from an API and style with a Lottie animation."
    },

    {
        "title": "Subtle Effect on scroll",
        "tech": "HTML, CSS, JavaScript",
        "image": "./assets/day12.png",
        "button-git": "Github",
        "button-demo":"Demo",
        "githubLink": "https://github.com/majazimnoch/code-day12",
        "demoLink": "https://teal-chimera-e4ca1d.netlify.app/",
        "comment": "While scrolling down the page, we see a subtle effect of sliding objects, done with JavaScript."
    },

    {
        "title": "Art Generator",
        "tech": "HTML, CSS, JavaScript, API",
        "image": "./assets/day13.png",
        "button-git": "Github",
        "button-demo":"Demo",
        "githubLink": "https://github.com/majazimnoch/code-day13",
        "demoLink": "https://fastidious-babka-6479df.netlify.app/",
        "comment": "Here I use a public API from the Art Institute of Chicago and display a random artwork from their base."
    },

    {
        "title": "Ticket Counter",
        "tech": "React, React Hook 'useState'",
        "image": "./assets/day14.png",
        "button-git": "Github",
        "button-demo":"Demo",
        "githubLink": "https://github.com/majazimnoch/code-day14",
        "demoLink": "https://sparkling-strudel-cea7aa.netlify.app/",
        "comment": "I practise useState hook in React to create a ticket counter."
    },

    {
        "title": "Following design...",
        "tech": "React, Behance",
        "image": "./assets/day15.png",
        "button-git": "Github",
        "button-demo":"Demo",
        "githubLink": "https://github.com/majazimnoch/code-day15",
        "demoLink": "https://coruscating-profiterole-4c3f9e.netlify.app/",
        "comment": "I found a nice design on Behance and I created a component (hero) based on the design."
    },

    {
        "title": "Geography Quiz",
        "tech": "React, Hook 'useState', 'useRef'",
        "image": "./assets/day16.png",
        "button-git": "Github",
        "button-demo":"Demo",
        "githubLink": "https://github.com/majazimnoch/code-day16",
        "demoLink": "https://startling-jalebi-1a3618.netlify.app/",
        "comment": "I use React hooks, useState and useRef, to create a functional quiz about geography."
    },

    {
        "title": "Fetching info with useEffect",
        "tech": "React, Hook 'useState', 'useEffect', API",
        "image": "./assets/day17.png",
        "button-git": "Github",
        "button-demo":"Demo",
        "githubLink": "https://github.com/majazimnoch/code-day17-18",
        "demoLink": "https://splendorous-seahorse-9257d3.netlify.app/",
        "comment": "I use React hooks, useState and useEffect, to fetch info from json placeholder."
    },

    {
        "title": "Blobs and animation",
        "tech": "HTML, CSS, Blobs shapes",
        "image": "./assets/day19.png",
        "button-git": "Github",
        "button-demo":"Demo",
        "githubLink": "https://github.com/majazimnoch/code-day19",
        "demoLink": "https://super-clafoutis-1eb260.netlify.app/",
        "comment": "I give it a try and make div with irregular shapes, such as blobs. I also use keyframes animations."
    },

    {
        "title": "Cookies consent banner",
        "tech": "HTML, CSS, JavaScript",
        "image": "./assets/day20.png",
        "button-git": "Github",
        "button-demo":"Demo",
        "githubLink": "https://github.com/majazimnoch/code-day20",
        "demoLink": "https://zippy-ganache-685ed8.netlify.app/",
        "comment": "Practising a common cookie banner with pure JS."
    },


    {
        "title": "Styled cards",
        "tech": "HTML, CSS",
        "image": "./assets/day21.png",
        "button-git": "Github",
        "button-demo":"Demo",
        "githubLink": "https://github.com/majazimnoch/code-day21",
        "demoLink": "https://bejewelled-dragon-4a63c0.netlify.app/",
        "comment": "Playing around with CSS to make interesting, colorful and fun containers."
    },

    {
        "title": "Flashcards",
        "tech": "HTML, CSS",
        "image": "./assets/day22.png",
        "button-git": "Github",
        "button-demo":"Demo",
        "githubLink": "https://github.com/majazimnoch/code-day22",
        "demoLink": "https://lighthearted-lamington-e3c3ef.netlify.app/",
        "comment": "Using CSS to make flashcards. Trying 'transform-style' css property."
    }, 

    {
        "title": "To-do list",
        "tech": "HTML, CSS, Vue, features like: ref, watch, onMounted, computed",
        "image": "./assets/day23.png",
        "button-git": "Github",
        "button-demo":"Demo",
        "githubLink": "https://github.com/majazimnoch/code-day23-24-25",
        "demoLink": "https://hilarious-snickerdoodle-fd4dd4.netlify.app/",
        "comment": "My first Vue heavy project. I use some features provided by the framework like ref, watch, onMounted, computed."
    },

    {
        "title": "Tic Tac Toe Game",
        "tech": "HTML, CSS, JavaScript",
        "image": "./assets/day26.png",
        "button-git": "Github",
        "button-demo":"Demo",
        "githubLink": "https://github.com/majazimnoch/code-day26",
        "demoLink": "https://thriving-hamster-649c61.netlify.app/",
        "comment": "I wanted to practise more of JS functions, conditions and methods and building the tic tac toe game offers it all."
    },

    {
        "title": "Count and Switch",
        "tech": "HTML, CSS, Vue",
        "image": "./assets/day27.png",
        "button-git": "Github",
        "button-demo":"Demo",
        "githubLink": "https://github.com/majazimnoch/code-day27",
        "demoLink": "https://jazzy-sunburst-a46daa.netlify.app/",
        "comment": "Learning more about Vue. Increasing value and switching a word with Vue."
    },

    {
        "title": "Panic Website",
        "tech": "HTML, CSS, JavaScript",
        "image": "./assets/day28.png",
        "button-git": "Github",
        "button-demo":"Demo",
        "githubLink": "https://github.com/majazimnoch/code-day28",
        "demoLink": "https://heydrama.netlify.app/",
        "comment": "I was playing around with some JavScript built-in methods and I came up with an idea for this website."
    },

    {
        "title": "Accordion & Lemurs",
        "tech": "Vue, HTML, CSS",
        "image": "./assets/day29.png",
        "button-git": "Github",
        "button-demo":"Demo",
        "githubLink": "https://github.com/majazimnoch/code-day29",
        "demoLink": "https://vue-lemurs.netlify.app/",
        "comment": "Learning more about conditional rendering in Vue and about lovely lemurs."
    },

    {
        "title": "QR Code Generator",
        "tech": "HTML, CSS, JavaScript, API",
        "image": "./assets/day30.png",
        "button-git": "Github",
        "button-demo":"Demo",
        "githubLink": "https://github.com/majazimnoch/code-day30",
        "demoLink": "https://qr-all.netlify.app/",
        "comment": "It's a very easy and useful project, which requires fetching from a public QR code API."
    }, 

    {
        "title": "Calculate Life Path Number App",
        "tech": "HTML, CSS, JavaScript, LottieFiles",
        "image": "./assets/day31.png",
        "button-git": "Github",
        "button-demo":"Demo",
        "githubLink": "https://github.com/majazimnoch/code-day31",
        "demoLink": "https://melodic-moxie-23f251.netlify.app/",
        "comment": "As I am into numerology I finally made an app which enables calculating quickly someone's life path number and learning more about their personality."
    }

]